{
  "project_info": {
    "project_number": "390093630162",
    "project_id": "workcalendar240805",
    "storage_bucket": "workcalendar240805.appspot.com"
  },
  "client": [
    {
      "client_info": {
        "mobilesdk_app_id": "1:390093630162:android:ea523a77d2cc5154619b0b",
        "android_client_info": {
          "package_name": "com.app.calendar_project_240727"
        }
      },
      "oauth_client": [],
      "api_key": [
        {
          "current_key": "AIzaSyBM7H-zqpK9xI9Y0BVnazW5blL8tOOEj0E"
        }
      ],
      "services": {
        "appinvite_service": {
          "other_platform_oauth_client": []
        }
      }
    },
    {
      "client_info": {
        "mobilesdk_app_id": "1:390093630162:android:a006140a3976e3c1619b0b",
        "android_client_info": {
          "package_name": "com.example.calendar_project_240727"
        }
      },
      "oauth_client": [],
      "api_key": [
        {
          "current_key": "AIzaSyBM7H-zqpK9xI9Y0BVnazW5blL8tOOEj0E"
        }
      ],
      "services": {
        "appinvite_service": {
          "other_platform_oauth_client": []
        }
      }
    }
  ],
  "configuration_version": "1"
}